apiverve_bible/__init__.py
apiverve_bible/apiClient.py
apiverve_bible/exceptions.py
apiverve_bible/setup.py
apiverve_bible/setup_dep.py
apiverve_bible/tests/__init__.py
apiverve_bible/tests/test_api.py
apiverve_bible-1.1.8.dist-info/LICENSE
apiverve_bible-1.1.8.dist-info/METADATA
apiverve_bible-1.1.8.dist-info/WHEEL
apiverve_bible-1.1.8.dist-info/top_level.txt
apiverve_bible-1.1.8.dist-info/RECORD
